<xml xmlns="http://www.w3.org/1999/xhtml"><block type="root_block_ui_builder_button_onClick_handler" id="QI+l=hB)RJ+}F5oN@O/x" deletable="false" x="73" y="66"><statement name="statements_code"><block type="controls_if" id="yBTrOzWuj!SPqmBS3|}3"><value name="IF0"><block type="logic_compare" id="L%*B3?ru}BEFq|]l/6jt"><field name="OP">NEQ</field><value name="A"><block type="get_counter_value" id=";rrPIwAXTVU[L)v$!Xw("><value name="name"><shadow type="text" id="~.3N/.]7WWB6n5qf.VnM"><field name="TEXT">len</field></shadow></value></block></value><value name="B"><block type="math_number" id="4zapX~|#!!vV}^U@F0im"><field name="NUM">0</field></block></value></block></value><statement name="DO0"><block type="delete_data_from_cache" id="h1dn*7?C@9n}co8$3v/:"><value name="name"><shadow type="text" id="U_`sD(RM[{eF2O@WVSK."><field name="TEXT">7</field></shadow></value><next><block type="decrement_counter" id="5Aj%4qphP@,E!f;9bq.6"><mutation has_output="false"></mutation><field name="connections_toggler">FALSE</field><field name="counterFn">decrementAndGet</field><value name="name"><shadow type="text" id="IO#YV{};1pH,W$y!=dou"><field name="TEXT">len</field></shadow></value></block></next></block></statement><next><block type="component_action_block_app_router_goto_page" id="K03]o%RtW9nVK2p!I2hs"><value name="pageName"><shadow type="text" id="/)][^r}Vncuq_%3-VJNl"><field name="TEXT">WelcomePage</field></shadow></value></block></next></block></statement></block></xml>